tornadoredis/__init__.py
tornadoredis/backports.py
tornadoredis/client.py
tornadoredis/connection.py
tornadoredis/exceptions.py
tornadoredis/pubsub.py
tornadoredis-2.5.1.dist-info/DESCRIPTION.rst
tornadoredis-2.5.1.dist-info/METADATA
tornadoredis-2.5.1.dist-info/RECORD
tornadoredis-2.5.1.dist-info/WHEEL
tornadoredis-2.5.1.dist-info/metadata.json
tornadoredis-2.5.1.dist-info/top_level.txt
